<?xml version="1.0" encoding="UTF-8"?>
<data>
    <AU_MLLPCONFIGURATION>
        <au_modifiedBy><![CDATA[IndigoUser:127000000001107055536473900001]]></au_modifiedBy>
        <au_activeVersion><![CDATA[true]]></au_activeVersion>
        <au_projectOwner><![CDATA[Project:872746795543822336]]></au_projectOwner>
        <au_selectTransactionId><![CDATA[]]></au_selectTransactionId>
        <au_synchronized><![CDATA[false]]></au_synchronized>
        <au_modifiedDate><![CDATA[2021-06-17 14:42:58.95]]></au_modifiedDate>
        <au_creationDate><![CDATA[2021-06-17 14:42:58.95]]></au_creationDate>
        <au_fileBaseLocation><![CDATA[/shubha]]></au_fileBaseLocation>
        <au_entityName><![CDATA[sks_Copy_Copy_Copy]]></au_entityName>
        <au_version><![CDATA[1]]></au_version>
        <au_positiveAckChar><![CDATA[06]]></au_positiveAckChar>
        <au_userOwner><![CDATA[IndigoUser:869913324479840256]]></au_userOwner>
        <au_connectionRetryCount><![CDATA[0]]></au_connectionRetryCount>
        <au_endTextChar><![CDATA[1C]]></au_endTextChar>
        <au_comments><![CDATA[null]]></au_comments>
        <au_startTextChar><![CDATA[0B]]></au_startTextChar>
        <au_revision><![CDATA[25947e59e27b0cf9a92dcd7822f7ec88d37c41ab]]></au_revision>
        <au_id><![CDATA[010240000067162394097895100014]]></au_id>
        <au_port><![CDATA[1]]></au_port>
        <au_negativeAckChar><![CDATA[15]]></au_negativeAckChar>
        <au_dataPollingFrequency><![CDATA[15$s]]></au_dataPollingFrequency>
        <au_ackPollingFrequency><![CDATA[1$s]]></au_ackPollingFrequency>
        <au_description><![CDATA[ss]]></au_description>
        <au_mode><![CDATA[Server]]></au_mode>
        <au_ignoreSubFolders><![CDATA[false]]></au_ignoreSubFolders>
        <au_permissionMask><![CDATA[770]]></au_permissionMask>
        <au_hostName><![CDATA[10.1.0.1]]></au_hostName>
        <au_activateFlag><![CDATA[false]]></au_activateFlag>
        <au_lastTextChar><![CDATA[0D]]></au_lastTextChar>
        <au_previousVersion><![CDATA[]]></au_previousVersion>
        <au_dataTimeOut><![CDATA[12$m]]></au_dataTimeOut>
        <au_ackTimeOut><![CDATA[1$s]]></au_ackTimeOut>
        <au_groupOwner><![CDATA[IndigoGroup:192168001075148181566048300002]]></au_groupOwner>
        <au_intervalBetweenRetry><![CDATA[1$m]]></au_intervalBetweenRetry>
    </AU_MLLPCONFIGURATION>
    <columnInfo dbtype="0">
        <column name="au_id" type="12"/>
        <column name="au_version" type="12"/>
        <column name="au_previousVersion" type="12"/>
        <column name="au_activeVersion" type="-7"/>
        <column name="au_entityName" type="12"/>
        <column name="au_userOwner" type="12"/>
        <column name="au_groupOwner" type="12"/>
        <column name="au_permissionMask" type="12"/>
        <column name="au_description" type="12"/>
        <column name="au_comments" type="12"/>
        <column name="au_modifiedBy" type="12"/>
        <column name="au_creationDate" type="93"/>
        <column name="au_modifiedDate" type="93"/>
        <column name="au_revision" type="12"/>
        <column name="au_synchronized" type="-7"/>
        <column name="au_projectOwner" type="12"/>
        <column name="au_hostName" type="-1"/>
        <column name="au_port" type="4"/>
        <column name="au_mode" type="12"/>
        <column name="au_connectionRetryCount" type="4"/>
        <column name="au_intervalBetweenRetry" type="12"/>
        <column name="au_startTextChar" type="12"/>
        <column name="au_endTextChar" type="12"/>
        <column name="au_lastTextChar" type="12"/>
        <column name="au_dataTimeOut" type="12"/>
        <column name="au_dataPollingFrequency" type="12"/>
        <column name="au_ackTimeOut" type="12"/>
        <column name="au_ackPollingFrequency" type="12"/>
        <column name="au_fileBaseLocation" type="12"/>
        <column name="au_selectTransactionId" type="12"/>
        <column name="au_activateFlag" type="-7"/>
        <column name="au_ignoreSubFolders" type="-7"/>
        <column name="au_positiveAckChar" type="12"/>
        <column name="au_negativeAckChar" type="12"/>
    </columnInfo>
</data>
